djangospam/__init__.py
djangospam/logger.py
djangospam/settings.py
djangospam/akismet/__init__.py
djangospam/akismet/moderator.py
djangospam/cookie/__init__.py
djangospam/cookie/middleware.py
djangospam/cookie/moderator.py
djangospam/cookie/urls.py
djangospam/cookie/views.py
djangospam/templates/djangospam/cookieform.html
djangospam/templates/djangospam/form.html
djangospam-1.1.5.dist-info/LICENSE.txt
djangospam-1.1.5.dist-info/METADATA
djangospam-1.1.5.dist-info/WHEEL
djangospam-1.1.5.dist-info/top_level.txt
djangospam-1.1.5.dist-info/RECORD
