Metadata-Version: 2.1
Name: djangospam
Version: 1.1.5
Summary: Django antispam module with invisible fake comment/contact    form, cookie based middleware and Akismet verification.
Home-page: https://github.com/leandroarndt/djangospam
Download-URL: https://github.com/leandroarndt/djangospam/archive/v1.1.5.tar.gz
Author: Leandro Arndt
Author-email: contato@caritasinveritate.teo.br
License: BSD
Project-URL: Bug tracker, https://github.com/leandroarndt/djangospam/issues
Keywords: django,spam,akismet,middleware
Platform: OS independent
Classifier: Development Status :: 5 - Production/Stable
Classifier: Environment :: Web Environment
Classifier: Framework :: Django
Classifier: Intended Audience :: Developers
Classifier: License :: OSI Approved :: BSD License
Classifier: Operating System :: OS Independent
Classifier: Programming Language :: Python
Classifier: Topic :: Internet :: WWW/HTTP
Classifier: Topic :: Internet :: WWW/HTTP :: Dynamic Content
Classifier: Topic :: Internet :: WWW/HTTP :: Site Management
Classifier: Topic :: Software Development :: Libraries :: Python Modules
Classifier: Programming Language :: Python :: 2
Classifier: Programming Language :: Python :: 3
Requires: django
License-File: LICENSE.txt
